{
  "posts": [
    { "sentimento": "amor", "referenciaImagem": "https://cdn.emojidex.com/emoji/seal/two_hearts.png" },
    { "sentimento": "alegria", "referenciaImagem": "https://emojipedia-us.s3.dualstack.us-west-1.amazonaws.com/thumbs/120/apple/325/beaming-face-with-smiling-eyes_1f601.png" },
    { "sentimento": "tristeza", "referenciaImagem": "https://emojipedia-us.s3.dualstack.us-west-1.amazonaws.com/thumbs/120/apple/325/loudly-crying-face_1f62d.png" }
  ],
  "profile": {
    "name": "joaofaria"
  }
}
